NekoGram/__init__.py
NekoGram/base_neko.py
NekoGram/filters.py
NekoGram/logger.py
NekoGram/menus.py
NekoGram/neko.py
NekoGram/router.py
NekoGram/utils.py
NekoGram/webhook.py
NekoGram/handlers/__init__.py
NekoGram/handlers/callback.py
NekoGram/handlers/message.py
NekoGram/storages/__init__.py
NekoGram/storages/base_storage.py
NekoGram/storages/memory_storage.py
NekoGram/storages/mysql/__init__.py
NekoGram/storages/mysql/mysql.py
NekoGram/storages/mysql/tables.json
NekoGram/storages/pg/__init__.py
NekoGram/storages/pg/pg.py
NekoGram/text_processors/__init__.py
NekoGram/text_processors/base_processor.py
NekoGram/text_processors/json_processor.py
NekoGram/widgets/__init__.py
NekoGram/widgets/broadcast/__init__.py
NekoGram/widgets/broadcast/formatters.py
NekoGram/widgets/broadcast/functions.py
NekoGram/widgets/broadcast/util.py
NekoGram/widgets/broadcast/utils.py
NekoGram/widgets/broadcast/translations/en.json
NekoGram/widgets/broadcast/translations/pl.json
NekoGram/widgets/broadcast/translations/ru.json
NekoGram/widgets/broadcast/translations/uk.json
NekoGram/widgets/languages/__init__.py
NekoGram/widgets/languages/formatters.py
NekoGram/widgets/languages/functions.py
NekoGram/widgets/languages/replacements.json
NekoGram/widgets/languages/util.py
NekoGram/widgets/languages/translations/en.json
NekoGram/widgets/languages/translations/he.json
NekoGram/widgets/languages/translations/pl.json
NekoGram/widgets/languages/translations/ru.json
NekoGram/widgets/languages/translations/uk.json
NekoGram/widgets/stats/__init__.py
NekoGram/widgets/stats/formatters.py
NekoGram/widgets/stats/functions.py
NekoGram/widgets/stats/util.py
NekoGram/widgets/stats/sql/tables.json
NekoGram/widgets/stats/translations/en.json
NekoGram-2.1.0.dist-info/LICENSE
NekoGram-2.1.0.dist-info/METADATA
NekoGram-2.1.0.dist-info/WHEEL
NekoGram-2.1.0.dist-info/top_level.txt
NekoGram-2.1.0.dist-info/RECORD
