Metadata-Version: 2.1
Name: NekoGram
Version: 2.1.0
Summary: Creating bots has never been simpler.
Author-email: lyteloli <me@lyteloli.space>
License: MIT License
Project-URL: Homepage, https://github.com/lyteloli/NekoGram
Project-URL: Bug Tracker, https://github.com/lyteloli/NekoGram/issues
Classifier: Programming Language :: Python :: 3
Classifier: License :: OSI Approved :: MIT License
Classifier: Operating System :: OS Independent
Classifier: Intended Audience :: Developers
Classifier: Topic :: Software Development
Requires-Python: >=3.9
License-File: LICENSE
Requires-Dist: aiogram (~=2.23.1)
Requires-Dist: importlib-resources (~=5.10.0)
